{
  "generatedAt": "2026-05-04T12:42:51.534Z",
  "collections": [
    {
      "name": "users",
      "type": "auth",
      "apiRules": {
        "list": "id = @request.auth.id || @request.auth.role = 'admin'",
        "view": "id = @request.auth.id || @request.auth.role = 'admin'",
        "create": "",
        "update": "id = @request.auth.id || @request.auth.role = 'admin'",
        "delete": "id = @request.auth.id || @request.auth.role = 'admin'"
      },
      "fields": [
        {
          "name": "name",
          "type": "text",
          "required": false,
          "system": false
        },
        {
          "name": "avatar",
          "type": "file",
          "required": false,
          "system": false
        },
        {
          "name": "created",
          "type": "autodate",
          "required": false,
          "system": false,
          "autodateTriggers": ["onCreate"]
        },
        {
          "name": "updated",
          "type": "autodate",
          "required": false,
          "system": false,
          "autodateTriggers": ["onCreate", "onUpdate"]
        },
        {
          "name": "role",
          "type": "select",
          "required": true,
          "system": false,
          "selectValues": ["admin", "membro", "cliente"]
        },
        {
          "name": "lastActive",
          "type": "date",
          "required": false,
          "system": false
        },
        {
          "name": "dashboard_layout",
          "type": "json",
          "required": false,
          "system": false
        },
        {
          "name": "theme",
          "type": "select",
          "required": false,
          "system": false,
          "selectValues": ["light", "dark"]
        }
      ],
      "indexes": [
        "CREATE UNIQUE INDEX `idx_tokenKey__pb_users_auth_` ON `users` (`tokenKey`)",
        "CREATE UNIQUE INDEX `idx_email__pb_users_auth_` ON `users` (`email`) WHERE `email` != ''"
      ]
    },
    {
      "name": "boards",
      "type": "base",
      "apiRules": {
        "list": "@request.auth.role = 'admin' || members ~ @request.auth.id",
        "view": "@request.auth.role = 'admin' || members ~ @request.auth.id",
        "create": "@request.auth.role = 'admin'",
        "update": "@request.auth.role = 'admin'",
        "delete": "@request.auth.role = 'admin'"
      },
      "fields": [
        {
          "name": "name",
          "type": "text",
          "required": true,
          "system": false
        },
        {
          "name": "description",
          "type": "text",
          "required": false,
          "system": false
        },
        {
          "name": "color",
          "type": "text",
          "required": false,
          "system": false
        },
        {
          "name": "icon",
          "type": "text",
          "required": false,
          "system": false
        },
        {
          "name": "client_name",
          "type": "text",
          "required": false,
          "system": false
        },
        {
          "name": "created_by",
          "type": "relation",
          "required": true,
          "system": false,
          "collectionRef": "users"
        },
        {
          "name": "archived",
          "type": "bool",
          "required": false,
          "system": false
        },
        {
          "name": "members",
          "type": "relation",
          "required": false,
          "system": false,
          "collectionRef": "users"
        },
        {
          "name": "created",
          "type": "autodate",
          "required": false,
          "system": false,
          "autodateTriggers": ["onCreate"]
        },
        {
          "name": "updated",
          "type": "autodate",
          "required": false,
          "system": false,
          "autodateTriggers": ["onCreate", "onUpdate"]
        }
      ],
      "indexes": ["CREATE INDEX `idx_boards_archived` ON `boards` (archived)"]
    },
    {
      "name": "columns",
      "type": "base",
      "apiRules": {
        "list": "@request.auth.role = \"admin\" || board_id.members ~ @request.auth.id",
        "view": "@request.auth.role = \"admin\" || board_id.members ~ @request.auth.id",
        "create": "@request.auth.role = \"admin\" || board_id.members ~ @request.auth.id",
        "update": "@request.auth.role = \"admin\" || board_id.members ~ @request.auth.id",
        "delete": "@request.auth.role = \"admin\" || board_id.members ~ @request.auth.id"
      },
      "fields": [
        {
          "name": "board_id",
          "type": "relation",
          "required": true,
          "system": false,
          "collectionRef": "boards"
        },
        {
          "name": "name",
          "type": "text",
          "required": true,
          "system": false
        },
        {
          "name": "sort_order",
          "type": "number",
          "required": false,
          "system": false
        },
        {
          "name": "color",
          "type": "text",
          "required": false,
          "system": false
        },
        {
          "name": "created",
          "type": "autodate",
          "required": false,
          "system": false,
          "autodateTriggers": ["onCreate"]
        },
        {
          "name": "updated",
          "type": "autodate",
          "required": false,
          "system": false,
          "autodateTriggers": ["onCreate", "onUpdate"]
        }
      ],
      "indexes": ["CREATE INDEX `idx_columns_board_order` ON `columns` (board_id, sort_order)"]
    },
    {
      "name": "cards",
      "type": "base",
      "apiRules": {
        "list": "@request.auth.id != ''",
        "view": "@request.auth.id != ''",
        "create": "@request.auth.id != ''",
        "update": "@request.auth.id != ''",
        "delete": "@request.auth.id != ''"
      },
      "fields": [
        {
          "name": "column_id",
          "type": "relation",
          "required": true,
          "system": false,
          "collectionRef": "columns"
        },
        {
          "name": "board_id",
          "type": "relation",
          "required": true,
          "system": false,
          "collectionRef": "boards"
        },
        {
          "name": "title",
          "type": "text",
          "required": true,
          "system": false
        },
        {
          "name": "description",
          "type": "editor",
          "required": false,
          "system": false
        },
        {
          "name": "due_date",
          "type": "date",
          "required": false,
          "system": false
        },
        {
          "name": "sort_order",
          "type": "number",
          "required": false,
          "system": false
        },
        {
          "name": "created_by",
          "type": "relation",
          "required": false,
          "system": false,
          "collectionRef": "users"
        },
        {
          "name": "completed",
          "type": "bool",
          "required": false,
          "system": false
        },
        {
          "name": "created",
          "type": "autodate",
          "required": false,
          "system": false,
          "autodateTriggers": ["onCreate"]
        },
        {
          "name": "updated",
          "type": "autodate",
          "required": false,
          "system": false,
          "autodateTriggers": ["onCreate", "onUpdate"]
        },
        {
          "name": "archived",
          "type": "bool",
          "required": false,
          "system": false
        }
      ],
      "indexes": []
    },
    {
      "name": "labels",
      "type": "base",
      "apiRules": {
        "list": "@request.auth.id != ''",
        "view": "@request.auth.id != ''",
        "create": "@request.auth.id != ''",
        "update": "@request.auth.id != ''",
        "delete": "@request.auth.id != ''"
      },
      "fields": [
        {
          "name": "board_id",
          "type": "relation",
          "required": true,
          "system": false,
          "collectionRef": "boards"
        },
        {
          "name": "name",
          "type": "text",
          "required": true,
          "system": false
        },
        {
          "name": "color",
          "type": "text",
          "required": true,
          "system": false
        },
        {
          "name": "created",
          "type": "autodate",
          "required": false,
          "system": false,
          "autodateTriggers": ["onCreate"]
        },
        {
          "name": "updated",
          "type": "autodate",
          "required": false,
          "system": false,
          "autodateTriggers": ["onCreate", "onUpdate"]
        }
      ],
      "indexes": []
    },
    {
      "name": "card_labels",
      "type": "base",
      "apiRules": {
        "list": "@request.auth.id != ''",
        "view": "@request.auth.id != ''",
        "create": "@request.auth.id != ''",
        "update": "@request.auth.id != ''",
        "delete": "@request.auth.id != ''"
      },
      "fields": [
        {
          "name": "card_id",
          "type": "relation",
          "required": true,
          "system": false,
          "collectionRef": "cards"
        },
        {
          "name": "label_id",
          "type": "relation",
          "required": true,
          "system": false,
          "collectionRef": "labels"
        },
        {
          "name": "created",
          "type": "autodate",
          "required": false,
          "system": false,
          "autodateTriggers": ["onCreate"]
        },
        {
          "name": "updated",
          "type": "autodate",
          "required": false,
          "system": false,
          "autodateTriggers": ["onCreate", "onUpdate"]
        }
      ],
      "indexes": []
    },
    {
      "name": "card_members",
      "type": "base",
      "apiRules": {
        "list": "@request.auth.id != ''",
        "view": "@request.auth.id != ''",
        "create": "@request.auth.id != ''",
        "update": "@request.auth.id != ''",
        "delete": "@request.auth.id != ''"
      },
      "fields": [
        {
          "name": "card_id",
          "type": "relation",
          "required": true,
          "system": false,
          "collectionRef": "cards"
        },
        {
          "name": "user_id",
          "type": "relation",
          "required": true,
          "system": false,
          "collectionRef": "users"
        },
        {
          "name": "created",
          "type": "autodate",
          "required": false,
          "system": false,
          "autodateTriggers": ["onCreate"]
        },
        {
          "name": "updated",
          "type": "autodate",
          "required": false,
          "system": false,
          "autodateTriggers": ["onCreate", "onUpdate"]
        }
      ],
      "indexes": []
    },
    {
      "name": "attachments",
      "type": "base",
      "apiRules": {
        "list": "@request.auth.id != ''",
        "view": "@request.auth.id != ''",
        "create": "@request.auth.id != ''",
        "update": "@request.auth.id != ''",
        "delete": "@request.auth.id != ''"
      },
      "fields": [
        {
          "name": "card_id",
          "type": "relation",
          "required": true,
          "system": false,
          "collectionRef": "cards"
        },
        {
          "name": "file",
          "type": "file",
          "required": false,
          "system": false
        },
        {
          "name": "name",
          "type": "text",
          "required": false,
          "system": false
        },
        {
          "name": "type",
          "type": "text",
          "required": false,
          "system": false
        },
        {
          "name": "size",
          "type": "number",
          "required": false,
          "system": false
        },
        {
          "name": "user_id",
          "type": "relation",
          "required": false,
          "system": false,
          "collectionRef": "users"
        },
        {
          "name": "created",
          "type": "autodate",
          "required": false,
          "system": false,
          "autodateTriggers": ["onCreate"]
        },
        {
          "name": "updated",
          "type": "autodate",
          "required": false,
          "system": false,
          "autodateTriggers": ["onCreate", "onUpdate"]
        }
      ],
      "indexes": []
    },
    {
      "name": "checklist_items",
      "type": "base",
      "apiRules": {
        "list": "@request.auth.id != ''",
        "view": "@request.auth.id != ''",
        "create": "@request.auth.id != ''",
        "update": "@request.auth.id != ''",
        "delete": "@request.auth.id != ''"
      },
      "fields": [
        {
          "name": "card_id",
          "type": "relation",
          "required": true,
          "system": false,
          "collectionRef": "cards"
        },
        {
          "name": "text",
          "type": "text",
          "required": true,
          "system": false
        },
        {
          "name": "completed",
          "type": "bool",
          "required": false,
          "system": false
        },
        {
          "name": "sort_order",
          "type": "number",
          "required": false,
          "system": false
        },
        {
          "name": "created",
          "type": "autodate",
          "required": false,
          "system": false,
          "autodateTriggers": ["onCreate"]
        },
        {
          "name": "updated",
          "type": "autodate",
          "required": false,
          "system": false,
          "autodateTriggers": ["onCreate", "onUpdate"]
        }
      ],
      "indexes": []
    },
    {
      "name": "comments",
      "type": "base",
      "apiRules": {
        "list": "@request.auth.id != ''",
        "view": "@request.auth.id != ''",
        "create": "@request.auth.id != ''",
        "update": "@request.auth.id != ''",
        "delete": "@request.auth.id != ''"
      },
      "fields": [
        {
          "name": "card_id",
          "type": "relation",
          "required": true,
          "system": false,
          "collectionRef": "cards"
        },
        {
          "name": "user_id",
          "type": "relation",
          "required": true,
          "system": false,
          "collectionRef": "users"
        },
        {
          "name": "content",
          "type": "text",
          "required": true,
          "system": false
        },
        {
          "name": "created",
          "type": "autodate",
          "required": false,
          "system": false,
          "autodateTriggers": ["onCreate"]
        },
        {
          "name": "updated",
          "type": "autodate",
          "required": false,
          "system": false,
          "autodateTriggers": ["onCreate", "onUpdate"]
        }
      ],
      "indexes": []
    },
    {
      "name": "activity_logs",
      "type": "base",
      "apiRules": {
        "list": "@request.auth.id != ''",
        "view": "@request.auth.id != ''",
        "create": "@request.auth.id != ''",
        "update": null,
        "delete": null
      },
      "fields": [
        {
          "name": "card_id",
          "type": "relation",
          "required": true,
          "system": false,
          "collectionRef": "cards"
        },
        {
          "name": "user_id",
          "type": "relation",
          "required": true,
          "system": false,
          "collectionRef": "users"
        },
        {
          "name": "action_type",
          "type": "select",
          "required": true,
          "system": false,
          "selectValues": [
            "creation",
            "move",
            "edit_title",
            "edit_desc",
            "label_add",
            "label_remove",
            "assignment_add",
            "assignment_remove",
            "attachment_add",
            "comment_add",
            "date_change",
            "completion"
          ]
        },
        {
          "name": "description",
          "type": "text",
          "required": false,
          "system": false
        },
        {
          "name": "created",
          "type": "autodate",
          "required": false,
          "system": false,
          "autodateTriggers": ["onCreate"]
        },
        {
          "name": "updated",
          "type": "autodate",
          "required": false,
          "system": false,
          "autodateTriggers": ["onCreate", "onUpdate"]
        }
      ],
      "indexes": []
    }
  ]
}
